{
    "other": [
        {
            "nanoid": "eSMkzAvr1JhXfB",
            "name": "Swarnavahini",
            "iptv_urls": [
                "https://jk3lz8xklw79-hls-live.5centscdn.com/live/6226f7cbe59e99a90b5cef6f94f966fd.sdp/playlist.m3u8"
            ],
            "youtube_urls": [],
            "language": "sin",
            "country": "lk",
            "isGeoBlocked": false
        },
        {
            "nanoid": "93ImfKCer0mJxB",
            "name": "Siyatha TV",
            "iptv_urls": [
                "https://rtmp01.voaplus.com/hls/6x6ik312qk4grfxocfcv.m3u8"
            ],
            "youtube_urls": [],
            "language": "sin",
            "country": "lk",
            "isGeoBlocked": false
        }
    ],
    "entertainment": [
        {
            "nanoid": "8GtOpx9EPmjKvR",
            "name": "Hiru TV",
            "iptv_urls": [
                "https://tv.hiruhost.com:1936/8012/8012/playlist.m3u8"
            ],
            "youtube_urls": [],
            "language": "sin",
            "country": "lk",
            "isGeoBlocked": false
        }
    ]
}